geofence_lib/__init__.py
geofence_lib/events.py
geofence_lib/geofencing.py
geofence_lib/utils.py
tests/__init__.py
tests/test_geofencing.py
GeoFenceLib-0.3.0.dist-info/LICENSE
GeoFenceLib-0.3.0.dist-info/METADATA
GeoFenceLib-0.3.0.dist-info/WHEEL
GeoFenceLib-0.3.0.dist-info/top_level.txt
GeoFenceLib-0.3.0.dist-info/RECORD
