Metadata-Version: 2.1
Name: GeoFenceLib
Version: 0.3.0
Summary: A Python library for geofencing with dynamic shape.
Author: Abhinav
Author-email: upstage.barrier_0x@icloud.com
Classifier: Programming Language :: Python :: 3
Classifier: License :: OSI Approved :: MIT License
Classifier: Operating System :: OS Independent
License-File: LICENSE
